pyrulent/__init__.py
pyrulent/engine.py
pyrulent/logic.py
rulent/__init__.py
rulent/engine.py
rulent/logic.py
tests/__init__.py
tests/test_engine.py
rulent-0.0.2.dist-info/LICENSE
rulent-0.0.2.dist-info/METADATA
rulent-0.0.2.dist-info/WHEEL
rulent-0.0.2.dist-info/top_level.txt
rulent-0.0.2.dist-info/RECORD
