Metadata-Version: 2.1
Name: rulent
Version: 0.0.2
Summary: A declarative rules engine.
Home-page: https://github.com/razaibi/pyrulent
Author: Raza Balbale
License: Apache 2.0
Project-URL: Documentation, https://github.com/razaibi/pyrulent/README.md
Project-URL: Source, https://github.com/razaibi/pyrulent
Project-URL: Tracker, https://github.com/razaibi/pyrulent/
License-File: LICENSE
Requires-Dist: pyyaml
Requires-Dist: pydantic
